{
  "author": {
    "name": "Angel Dhakal",
    "bio": "software developer passionate about creating efficient and scalable solutions."
  },
  "social": {
    "website": "https://codeangel.tech",
    "github": "https://github.com/andy4747",
    "linkedin": "https://linkedin.com/in/angeldhakal",
    "twitter": "https://x.com/andydl101"
  },
  "site": {
    "logo": "/images/logo.png",
    "favicon": "/favicon.ico"
  },
  "abouts": {
    "author": {
      "name": "Angel Dhakal",
      "bio": "Software developer passionate about creating efficient and scalable solutions."
    },
    "social": [
      {
        "name": "Website",
        "url": "https://codeangel.tech",
        "icon": "fas fa-globe"
      },
      {
        "name": "GitHub",
        "url": "https://github.com/andy4747",
        "icon": "fab fa-github"
      },
      {
        "name": "LinkedIn",
        "url": "https://linkedin.com/in/angeldhakal",
        "icon": "fab fa-linkedin-in"
      },
      {
        "name": "Twitter",
        "url": "https://x.com/andydl101",
        "icon": "fab fa-twitter"
      }
    ],
    "site": {
      "logo": "/images/logo.png",
      "favicon": "/favicon.ico"
    },
    "profile_image": "/images/angeldhakal.jpg",
    "skills": {
      "languages": [
        {
          "name": "Golang",
          "icon": "fab fa-golang"
        },
        {
          "name": "JavaScript",
          "icon": "fab fa-js-square"
        },
        {
          "name": "TypeScript",
          "icon": "fab fa-js"
        },
        {
          "name": "Python",
          "icon": "fab fa-python"
        },
        {
          "name": "Java",
          "icon": "fab fa-java"
        },
        {
          "name": "SQL",
          "icon": "fas fa-database"
        },
        {
          "name": "Bash",
          "icon": "fas fa-terminal"
        }
      ],
      "frameworks": [
        {
          "name": "Go Stdlib",
          "icon": "fab fa-golang"
        },
        {
          "name": "React",
          "icon": "fab fa-react"
        },
        {
          "name": "Next.js",
          "icon": "fab fa-react"
        },
        {
          "name": "REST",
          "icon": "fas fa-exchange-alt"
        },
        {
          "name": "GraphQL",
          "icon": "fas fa-project-diagram"
        },
        {
          "name": "Tailwind CSS",
          "icon": "fab fa-css3-alt"
        },
        {
          "name": "Hugo",
          "icon": "fas fa-h-square"
        },
        {
          "name": "Django",
          "icon": "fab fa-python"
        }
      ],
      "tools": [
        {
          "name": "AWS",
          "icon": "fab fa-aws"
        },
        {
          "name": "Terraform",
          "icon": "fas fa-globe"
        },
        {
          "name": "CI/CD",
          "icon": "fas fa-infinity"
        },
        {
          "name": "Firebase",
          "icon": "fas fa-fire"
        },
        {
          "name": "Git",
          "icon": "fab fa-git-alt"
        },
        {
          "name": "Linux",
          "icon": "fab fa-linux"
        },
        {
          "name": "Docker",
          "icon": "fab fa-docker"
        },
        {
          "name": "Traefik",
          "icon": "fas fa-network-wired"
        }
      ]
    },
    "experience": [
      {
        "title": "Software Developer",
        "company": "readytowork-corp",
        "location": "Remote (Tokyo, Japan)",
        "date": "July 2022 - Feb 2023"
      },
      {
        "title": "Software Developer Intern",
        "company": "Real Time Solutions Pvt. Ltd.",
        "location": "Lalitpur, Nepal",
        "date": "June 2021 - Oct 2021"
      }
    ],
    "education": [
      {
        "institution": "Fanshawe College",
        "degree": "Post Graduate in Technical Systems Analysis",
        "date": "Jan 2025 - Present"
      },
      {
        "institution": "Fanshawe College",
        "degree": "Post Graduate in Software Testing",
        "date": "Jan 2024 - Aug 2024"
      },
      {
        "institution": "London Metropolitan University",
        "degree": "BSc. Computing",
        "date": "Aug 2019 - May 2022"
      }
    ]
  }
}
